phonetic_fr/__init__.py
phonetic_fr/__main__.py
phonetic_fr/phonetic_fr.py
phonetic_fr-1.0.3.dist-info/licenses/LICENSE
phonetic_fr-1.0.3.dist-info/METADATA
phonetic_fr-1.0.3.dist-info/WHEEL
phonetic_fr-1.0.3.dist-info/entry_points.txt
phonetic_fr-1.0.3.dist-info/top_level.txt
phonetic_fr-1.0.3.dist-info/RECORD
